cosmicray/__init__.py
cosmicray/__version__.py
cosmicray/model.py
cosmicray/pprint.py
cosmicray/routes.py
cosmicray/util.py
cosmicray-0.0.13.dist-info/DESCRIPTION.rst
cosmicray-0.0.13.dist-info/METADATA
cosmicray-0.0.13.dist-info/RECORD
cosmicray-0.0.13.dist-info/WHEEL
cosmicray-0.0.13.dist-info/metadata.json
cosmicray-0.0.13.dist-info/top_level.txt
