Metadata-Version: 2.0
Name: cosmicray
Version: 0.0.13
Summary: Develop a client for your HTTP API and document its quirks and features
Home-page: https://github.com/somerovi/cosmicray
Author: Samir Omerovic
Author-email: somerovi@gmail.com
License: MIT
Platform: UNKNOWN
Classifier: License :: OSI Approved :: MIT License
Classifier: Programming Language :: Python
Classifier: Programming Language :: Python :: 2.6
Classifier: Programming Language :: Python :: 2.7
Classifier: Programming Language :: Python :: 3
Classifier: Programming Language :: Python :: 3.3
Classifier: Programming Language :: Python :: 3.4
Classifier: Programming Language :: Python :: 3.5
Classifier: Programming Language :: Python :: 3.6
Classifier: Programming Language :: Python :: Implementation :: CPython
Classifier: Programming Language :: Python :: Implementation :: PyPy
Requires-Dist: colorama (==0.3.9)
Requires-Dist: requests (==2.18.4)
Requires-Dist: six (==1.11.0)
